dash_drag_grid/DashboardItemResponsive.py
dash_drag_grid/ResponsiveGridLayout.py
dash_drag_grid/ToolBox2.py
dash_drag_grid/ToolBoxGrid.py
dash_drag_grid/ToolBoxGrid2.py
dash_drag_grid/__init__.py
dash_drag_grid/_imports_.py
dash_drag_grid/dash_drag_grid.min.js
dash_drag_grid/dash_drag_grid.min.js.map
dash_drag_grid/metadata.json
dash_drag_grid/package-info.json
dash_drag_grid-0.9.4.dev0.dist-info/LICENSE
dash_drag_grid-0.9.4.dev0.dist-info/METADATA
dash_drag_grid-0.9.4.dev0.dist-info/WHEEL
dash_drag_grid-0.9.4.dev0.dist-info/top_level.txt
dash_drag_grid-0.9.4.dev0.dist-info/RECORD
