Metadata-Version: 2.1
Name: dash_drag_grid
Version: 0.9.4.dev0
Summary: Draggable Toolbox grid based on react grid
Author: Simon Unterbusch <simonunterbusch@unterbusch.com>
License: MIT
Classifier: Framework :: Dash
License-File: LICENSE
